simple_s3/__init__.py
simple_s3-1.0.0.dist-info/METADATA
simple_s3-1.0.0.dist-info/WHEEL
simple_s3-1.0.0.dist-info/top_level.txt
simple_s3-1.0.0.dist-info/RECORD
