Metadata-Version: 2.1
Name: simple-s3
Version: 1.0.0
Summary: Simple S3 uploads
Home-page: https://github.com/julien-c/simple-s3
Author: Julien Chaumond
Author-email: chaumond@gmail.com
License: Apache
Keywords: s3
Platform: UNKNOWN
Classifier: Intended Audience :: Science/Research
Classifier: License :: OSI Approved :: Apache Software License
Classifier: Programming Language :: Python :: 3
Classifier: Topic :: Scientific/Engineering :: Artificial Intelligence
Requires-Python: >=3.5.0
Requires-Dist: boto3
Requires-Dist: requests
